pymyastuce/Lines.py
pymyastuce/Request.py
pymyastuce/Stations.py
pymyastuce/__init__.py
pymyastuce-0.0.3.dist-info/LICENSE
pymyastuce-0.0.3.dist-info/METADATA
pymyastuce-0.0.3.dist-info/WHEEL
pymyastuce-0.0.3.dist-info/top_level.txt
pymyastuce-0.0.3.dist-info/RECORD
